MANIFEST.in
README.md
setup.cfg
setup.py
versioneer.py
csirtg_domainsml/__init__.py
csirtg_domainsml/_version.py
csirtg_domainsml/constants.py
csirtg_domainsml/domain.py
csirtg_domainsml/train.py
csirtg_domainsml.egg-info/PKG-INFO
csirtg_domainsml.egg-info/SOURCES.txt
csirtg_domainsml.egg-info/dependency_links.txt
csirtg_domainsml.egg-info/entry_points.txt
csirtg_domainsml.egg-info/requires.txt
csirtg_domainsml.egg-info/top_level.txt
csirtg_domainsml/utils/__init__.py
data/blacklist.txt
data/model.pickle
data/model_py2.pickle
data/whitelist.txt
test/__init__.py
test/test_basics.py