Metadata-Version: 1.0
Name: csirtg-domainsml
Version: 0.0.0a5
Summary: CSIRTG Domains ML Framework
Home-page: https://github.com/csirtgadgets/csirtg-domainsml
Author: Wes Young
Author-email: wes@barely3am.com
License: MPLv2
Keywords: network,security
Platform: UNKNOWN
